irtranslate/__init__.py
irtranslate/exceptions.py
irtranslate/test.py
irtranslate/translator.py
irtranslate-2.1.0.dist-info/licenses/LICENSE
irtranslate-2.1.0.dist-info/METADATA
irtranslate-2.1.0.dist-info/WHEEL
irtranslate-2.1.0.dist-info/top_level.txt
irtranslate-2.1.0.dist-info/RECORD
